MANIFEST.in
README.rst
setup.py
zlib_wrapper/__init__.py
zlib_wrapper/compress.py
zlib_wrapper/decompress.py
zlib_wrapper.egg-info/PKG-INFO
zlib_wrapper.egg-info/SOURCES.txt
zlib_wrapper.egg-info/dependency_links.txt
zlib_wrapper.egg-info/not-zip-safe
zlib_wrapper.egg-info/top_level.txt