Metadata-Version: 1.0
Name: zlib-wrapper
Version: 0.1.2
Summary: Wrapper around zlib with custom header crc32.
Home-page: http://github.com/killswitch-GUI/zlib_format
Author: Alexander Rymdeko-Harvey
Author-email: lolyearight@cybersyndicates.com
License: GNU 3.0
Platform: UNKNOWN
